napari_dpr/__init__.py
napari_dpr/_widget.py
napari_dpr/dpr.py
napari_dpr/dpr_core.cp310-win_amd64.pyd
napari_dpr/dpr_core.cp311-win_amd64.pyd
napari_dpr/dpr_core.cp312-win_amd64.pyd
napari_dpr/dpr_core.cp313-win_amd64.pyd
napari_dpr/dpr_core.cp39-win_amd64.pyd
napari_dpr/dpr_core.cpp
napari_dpr/dpr_core.pyx
napari_dpr/napari.yaml
napari_dpr/run.dpr.py
napari_dpr-0.1.0.dist-info/METADATA
napari_dpr-0.1.0.dist-info/WHEEL
napari_dpr-0.1.0.dist-info/entry_points.txt
napari_dpr-0.1.0.dist-info/top_level.txt
napari_dpr-0.1.0.dist-info/RECORD
